README.md
pyproject.toml
setup.cfg
setup.py
kasperdb/__init__.py
kasperdb/config.py
kasperdb/db.py
kasperdb/functions.py
kasperdb/tests.py
kasperdb.egg-info/PKG-INFO
kasperdb.egg-info/SOURCES.txt
kasperdb.egg-info/dependency_links.txt
kasperdb.egg-info/not-zip-safe
kasperdb.egg-info/top_level.txt