Metadata-Version: 2.1
Name: kasperdb
Version: 1.7.2
Summary: Simple database for your project. Local database!!!
Home-page: https://github.com/KaSpEr-tv123/kasperdb.git
Author: KASPERENOK, MASEZEV
Author-email: KASPERENOK <dimakukic1@gmail.com>, MaseZev <csgomanagement1@gmail.com>
Project-URL: Homepage, https://github.com/KaSpEr-tv123/kasperdb
Project-URL: Bug Tracker, https://github.com/KaSpEr-tv123/kasperdb/issues
Project-URL: docs, https://kasper-tv123.github.io/kasperdb-docs
Classifier: Programming Language :: Python :: 3
Classifier: License :: OSI Approved :: MIT License
Classifier: Operating System :: OS Independent
Requires-Python: >=3.7
